BL_Python/database/__init__.py
BL_Python/database/config.py
BL_Python/database/dependency_injection.py
BL_Python/database/types.py
BL_Python/database/engine/__init__.py
BL_Python/database/engine/postgresql.py
BL_Python/database/engine/sqlite.py
BL_Python/database/migrations/__init__.py
BL_Python/database/migrations/alembic.py
BL_Python/database/migrations/alembic/README
BL_Python/database/migrations/alembic/__init__.py
BL_Python/database/migrations/alembic/__main__.py
BL_Python/database/migrations/alembic/_replacement_env.py
BL_Python/database/migrations/alembic/_replacement_env_setup.py
BL_Python/database/migrations/alembic/alembic.ini
BL_Python/database/migrations/alembic/bl_alembic.py
BL_Python/database/migrations/alembic/env.py
BL_Python/database/migrations/alembic/env_setup.py
BL_Python/database/migrations/alembic/script.py.mako
BL_Python/database/schema/__init__.py
BL_Python/database/schema/dialect.py
BL_Python/database/schema/metabase.py
BL_Python/database/schema/postgresql.py
BL_Python/database/schema/sqlite.py
BL_Python/database/testing/__init__.py
BL_Python/database/testing/config.py
test/unit/test_config.py
test/unit/test_dependency_injection.py
test/unit/test_engine.py
test/unit/test_schema.py
test/unit/migrations/alembic/test_bl_alembic.py
test/unit/migrations/alembic/test_env.py
test/unit/schema/test_dialect.py
typings/alembic/__init__.pyi
typings/alembic/__main__.pyi
typings/alembic/command.pyi
typings/alembic/config.pyi
typings/alembic/context.pyi
typings/alembic/environment.pyi
typings/alembic/migration.pyi
typings/alembic/op.pyi
typings/alembic/autogenerate/__init__.pyi
typings/alembic/autogenerate/api.pyi
typings/alembic/autogenerate/compare.pyi
typings/alembic/autogenerate/render.pyi
typings/alembic/autogenerate/rewriter.pyi
typings/alembic/ddl/__init__.pyi
typings/alembic/ddl/_autogen.pyi
typings/alembic/ddl/base.pyi
typings/alembic/ddl/impl.pyi
typings/alembic/ddl/mssql.pyi
typings/alembic/ddl/mysql.pyi
typings/alembic/ddl/oracle.pyi
BL_Python.database-0.2.1.dist-info/LICENSE.md
BL_Python.database-0.2.1.dist-info/METADATA
BL_Python.database-0.2.1.dist-info/WHEEL
BL_Python.database-0.2.1.dist-info/entry_points.txt
BL_Python.database-0.2.1.dist-info/top_level.txt
BL_Python.database-0.2.1.dist-info/RECORD
